{"match_id":"5f6c386b-0146-4a0f-8d49-e26cda479545","map_id":"AmbroseValley","date":"February_12","players":[{"user_id":"86b019b9-dd32-4fe0-baf4-174a1f51fa68","match_id":"5f6c386b-0146-4a0f-8d49-e26cda479545","map_id":"AmbroseValley","date":"February_12","is_bot":false,"events":[{"ts_norm_ms":0,"px":1090.12,"py":2976.4,"event":"Position"},{"ts_norm_ms":0,"px":901.24,"py":3598.36,"event":"BotKill"},{"ts_norm_ms":0,"px":909.79,"py":3599.69,"event":"Loot"}]}],"human_count":1,"bot_count":0,"total_events":3}