{"match_id":"7ab49019-c667-4263-bc6b-99c3b9492115","map_id":"Lockdown","date":"February_11","players":[{"user_id":"f58bd890-8687-478e-9934-302e79c19ef0","match_id":"7ab49019-c667-4263-bc6b-99c3b9492115","map_id":"Lockdown","date":"February_11","is_bot":false,"events":[{"ts_norm_ms":0,"px":6413.76,"py":2536.19,"event":"Position"},{"ts_norm_ms":15,"px":6527.96,"py":2670.86,"event":"Position"},{"ts_norm_ms":20,"px":6599.5,"py":2829.72,"event":"Position"},{"ts_norm_ms":22,"px":6599.5,"py":2829.72,"event":"Loot"},{"ts_norm_ms":23,"px":6599.5,"py":2829.72,"event":"Loot"},{"ts_norm_ms":25,"px":6641.99,"py":2897.13,"event":"Position"},{"ts_norm_ms":30,"px":6685.98,"py":2850.37,"event":"Position"},{"ts_norm_ms":35,"px":6644.6,"py":2814.63,"event":"Position"},{"ts_norm_ms":37,"px":6644.6,"py":2814.63,"event":"Loot"},{"ts_norm_ms":40,"px":6729.61,"py":2803.77,"event":"Position"},{"ts_norm_ms":46,"px":6729.61,"py":2803.77,"event":"Loot"},{"ts_norm_ms":50,"px":6747.78,"py":2780.05,"event":"Position"},{"ts_norm_ms":55,"px":6747.52,"py":2850.02,"event":"Position"},{"ts_norm_ms":66,"px":6756.43,"py":2935.47,"event":"Position"},{"ts_norm_ms":71,"px":6670.84,"py":2990.05,"event":"Position"},{"ts_norm_ms":76,"px":6585.06,"py":3005.86,"event":"Position"},{"ts_norm_ms":81,"px":6582.2,"py":2934.22,"event":"Position"},{"ts_norm_ms":83,"px":6515.07,"py":2903.31,"event":"BotKill"},{"ts_norm_ms":86,"px":6505.99,"py":2872.32,"event":"Position"},{"ts_norm_ms":86,"px":6510.28,"py":2869.01,"event":"Loot"},{"ts_norm_ms":87,"px":6504.22,"py":2868.18,"event":"Loot"},{"ts_norm_ms":91,"px":6540.24,"py":2888.4,"event":"Position"},{"ts_norm_ms":92,"px":6540.24,"py":2888.4,"event":"Loot"},{"ts_norm_ms":96,"px":6476.29,"py":2923.2,"event":"Position"},{"ts_norm_ms":97,"px":6476.29,"py":2923.2,"event":"Loot"},{"ts_norm_ms":98,"px":6476.29,"py":2923.2,"event":"Loot"},{"ts_norm_ms":101,"px":6539.92,"py":2932.05,"event":"Position"},{"ts_norm_ms":102,"px":6539.92,"py":2932.05,"event":"Loot"},{"ts_norm_ms":106,"px":6660.85,"py":2962.69,"event":"Position"},{"ts_norm_ms":111,"px":6762.65,"py":3122.02,"event":"Position"},{"ts_norm_ms":126,"px":6767.0,"py":3222.44,"event":"Position"},{"ts_norm_ms":131,"px":6712.2,"py":3442.52,"event":"Position"},{"ts_norm_ms":146,"px":6599.24,"py":3571.54,"event":"Position"},{"ts_norm_ms":151,"px":6540.43,"py":3705.81,"event":"Position"},{"ts_norm_ms":156,"px":6580.13,"py":3829.93,"event":"Position"},{"ts_norm_ms":159,"px":6580.74,"py":3831.63,"event":"Loot"},{"ts_norm_ms":161,"px":6595.53,"py":3921.9,"event":"Position"},{"ts_norm_ms":166,"px":6664.95,"py":3918.15,"event":"Position"}]}],"human_count":1,"bot_count":0,"total_events":38}