{"match_id":"8fd93d4e-038a-4e78-9d2d-ea89884bdc49","map_id":"AmbroseValley","date":"February_11","players":[{"user_id":"61671c88-dad2-48b9-80f2-bc66bca496cb","match_id":"8fd93d4e-038a-4e78-9d2d-ea89884bdc49","map_id":"AmbroseValley","date":"February_11","is_bot":false,"events":[{"ts_norm_ms":0,"px":2922.75,"py":1024.6,"event":"Position"},{"ts_norm_ms":0,"px":2709.16,"py":1075.71,"event":"Loot"},{"ts_norm_ms":0,"px":1978.44,"py":925.17,"event":"BotKilled"}]}],"human_count":1,"bot_count":0,"total_events":3}