{"match_id":"95e8481c-de84-4a79-be11-624e936ae4c8","map_id":"AmbroseValley","date":"February_10","players":[{"user_id":"1f62e018-e85e-4317-b72f-696e6e01ab9a","match_id":"95e8481c-de84-4a79-be11-624e936ae4c8","map_id":"AmbroseValley","date":"February_10","is_bot":false,"events":[{"ts_norm_ms":0,"px":3058.38,"py":2263.24,"event":"Position"},{"ts_norm_ms":20,"px":2938.93,"py":2273.99,"event":"Position"},{"ts_norm_ms":25,"px":2916.56,"py":2292.33,"event":"Position"},{"ts_norm_ms":30,"px":2863.48,"py":2274.46,"event":"Position"},{"ts_norm_ms":35,"px":2857.91,"py":2152.06,"event":"Position"},{"ts_norm_ms":40,"px":2767.63,"py":2068.29,"event":"Position"},{"ts_norm_ms":45,"px":2693.66,"py":2031.11,"event":"Position"},{"ts_norm_ms":50,"px":2638.13,"py":2018.74,"event":"Position"},{"ts_norm_ms":55,"px":2528.3,"py":2008.0,"event":"Position"},{"ts_norm_ms":60,"px":2571.56,"py":2007.09,"event":"Position"},{"ts_norm_ms":65,"px":2478.76,"py":2034.23,"event":"Position"},{"ts_norm_ms":70,"px":2380.23,"py":2039.84,"event":"Position"},{"ts_norm_ms":75,"px":2332.31,"py":2077.24,"event":"Position"},{"ts_norm_ms":80,"px":2325.38,"py":2087.91,"event":"Position"},{"ts_norm_ms":85,"px":2310.68,"py":2140.19,"event":"Position"},{"ts_norm_ms":90,"px":2328.53,"py":2193.4,"event":"Position"},{"ts_norm_ms":96,"px":2365.35,"py":2216.39,"event":"Position"},{"ts_norm_ms":100,"px":2329.27,"py":2263.43,"event":"Position"},{"ts_norm_ms":105,"px":2265.98,"py":2324.97,"event":"Position"},{"ts_norm_ms":107,"px":2290.34,"py":2332.37,"event":"BotKill"},{"ts_norm_ms":110,"px":2255.85,"py":2322.96,"event":"Position"},{"ts_norm_ms":131,"px":2199.47,"py":2412.5,"event":"Position"},{"ts_norm_ms":136,"px":2220.21,"py":2431.22,"event":"Position"},{"ts_norm_ms":138,"px":2213.33,"py":2424.36,"event":"Loot"},{"ts_norm_ms":141,"px":2241.33,"py":2418.06,"event":"Position"},{"ts_norm_ms":146,"px":2232.67,"py":2470.3,"event":"Position"},{"ts_norm_ms":151,"px":2197.84,"py":2445.08,"event":"Position"},{"ts_norm_ms":161,"px":2212.02,"py":2440.76,"event":"Position"},{"ts_norm_ms":166,"px":2204.0,"py":2423.98,"event":"Position"},{"ts_norm_ms":171,"px":2226.24,"py":2421.77,"event":"Position"},{"ts_norm_ms":176,"px":2195.0,"py":2393.51,"event":"Position"},{"ts_norm_ms":181,"px":2170.46,"py":2441.02,"event":"Position"},{"ts_norm_ms":186,"px":2158.44,"py":2473.77,"event":"Position"},{"ts_norm_ms":191,"px":2183.51,"py":2466.84,"event":"Position"},{"ts_norm_ms":196,"px":2255.33,"py":2411.48,"event":"Position"},{"ts_norm_ms":198,"px":2280.25,"py":2414.23,"event":"BotKill"},{"ts_norm_ms":201,"px":2328.19,"py":2390.33,"event":"Position"},{"ts_norm_ms":206,"px":2367.82,"py":2306.94,"event":"Position"},{"ts_norm_ms":207,"px":2367.82,"py":2306.94,"event":"Loot"},{"ts_norm_ms":210,"px":2367.82,"py":2306.94,"event":"Loot"},{"ts_norm_ms":216,"px":2323.92,"py":2404.43,"event":"Position"},{"ts_norm_ms":221,"px":2241.03,"py":2417.49,"event":"Position"},{"ts_norm_ms":226,"px":2218.27,"py":2444.18,"event":"Position"},{"ts_norm_ms":228,"px":2218.27,"py":2444.18,"event":"Loot"},{"ts_norm_ms":231,"px":2198.93,"py":2428.68,"event":"Position"},{"ts_norm_ms":236,"px":2192.4,"py":2451.68,"event":"Position"},{"ts_norm_ms":241,"px":2201.01,"py":2465.13,"event":"Position"},{"ts_norm_ms":251,"px":2214.1,"py":2452.27,"event":"Position"},{"ts_norm_ms":256,"px":2221.22,"py":2458.86,"event":"Position"},{"ts_norm_ms":261,"px":2234.13,"py":2449.6,"event":"Position"},{"ts_norm_ms":271,"px":2260.14,"py":2447.52,"event":"Position"},{"ts_norm_ms":276,"px":2257.98,"py":2427.43,"event":"Position"},{"ts_norm_ms":281,"px":2260.09,"py":2435.74,"event":"Position"},{"ts_norm_ms":286,"px":2253.99,"py":2455.23,"event":"Position"},{"ts_norm_ms":291,"px":2242.77,"py":2446.09,"event":"BotKilled"}]}],"human_count":1,"bot_count":0,"total_events":55}