{"match_id":"9b46bb18-c9c7-4f21-94d1-abfc2fb84887","map_id":"AmbroseValley","date":"February_11","players":[{"user_id":"2dee2f59-13fa-4447-889e-1ba2b2bbec63","match_id":"9b46bb18-c9c7-4f21-94d1-abfc2fb84887","map_id":"AmbroseValley","date":"February_11","is_bot":false,"events":[{"ts_norm_ms":0,"px":947.22,"py":437.6,"event":"Position"},{"ts_norm_ms":0,"px":1043.93,"py":595.34,"event":"Loot"},{"ts_norm_ms":0,"px":1605.24,"py":1394.98,"event":"BotKill"},{"ts_norm_ms":0,"px":1604.85,"py":1419.97,"event":"BotKilled"}]}],"human_count":1,"bot_count":0,"total_events":4}