{"match_id":"b3c04fcc-9903-4549-bd38-fbe9cf0631e6","map_id":"AmbroseValley","date":"February_14","players":[{"user_id":"10648aa3-b215-4c52-9577-5c5689a08939","match_id":"b3c04fcc-9903-4549-bd38-fbe9cf0631e6","map_id":"AmbroseValley","date":"February_14","is_bot":false,"events":[{"ts_norm_ms":0,"px":263.04,"py":2062.69,"event":"Position"},{"ts_norm_ms":10,"px":313.77,"py":1947.77,"event":"Position"},{"ts_norm_ms":15,"px":409.55,"py":1833.48,"event":"Position"},{"ts_norm_ms":20,"px":428.42,"py":1762.9,"event":"Position"},{"ts_norm_ms":20,"px":428.42,"py":1762.9,"event":"Loot"},{"ts_norm_ms":25,"px":367.34,"py":1761.82,"event":"Loot"},{"ts_norm_ms":25,"px":367.34,"py":1761.82,"event":"Position"},{"ts_norm_ms":26,"px":368.24,"py":1750.4,"event":"Loot"},{"ts_norm_ms":30,"px":394.36,"py":1726.8,"event":"Position"},{"ts_norm_ms":31,"px":380.19,"py":1722.71,"event":"Loot"},{"ts_norm_ms":35,"px":439.12,"py":1726.06,"event":"Position"},{"ts_norm_ms":36,"px":439.12,"py":1726.06,"event":"Loot"},{"ts_norm_ms":40,"px":425.91,"py":1717.5,"event":"Position"},{"ts_norm_ms":45,"px":398.65,"py":1691.33,"event":"Position"},{"ts_norm_ms":48,"px":400.98,"py":1689.54,"event":"Loot"},{"ts_norm_ms":50,"px":398.47,"py":1663.12,"event":"Position"},{"ts_norm_ms":52,"px":398.47,"py":1663.12,"event":"Loot"},{"ts_norm_ms":55,"px":461.52,"py":1613.68,"event":"Position"},{"ts_norm_ms":60,"px":567.02,"py":1715.02,"event":"Position"},{"ts_norm_ms":63,"px":624.61,"py":1673.08,"event":"Loot"},{"ts_norm_ms":65,"px":615.01,"py":1722.22,"event":"Position"},{"ts_norm_ms":70,"px":564.98,"py":1854.31,"event":"Loot"},{"ts_norm_ms":70,"px":564.98,"py":1854.31,"event":"Position"},{"ts_norm_ms":75,"px":680.88,"py":1872.5,"event":"Position"},{"ts_norm_ms":80,"px":803.69,"py":1906.56,"event":"Position"},{"ts_norm_ms":84,"px":823.36,"py":1944.52,"event":"Loot"},{"ts_norm_ms":85,"px":845.59,"py":1921.25,"event":"Position"},{"ts_norm_ms":90,"px":921.03,"py":2019.02,"event":"Position"},{"ts_norm_ms":96,"px":960.22,"py":2169.42,"event":"Position"},{"ts_norm_ms":101,"px":968.3,"py":2177.09,"event":"Position"},{"ts_norm_ms":105,"px":969.42,"py":2179.67,"event":"BotKill"},{"ts_norm_ms":111,"px":1031.5,"py":2191.63,"event":"Position"},{"ts_norm_ms":116,"px":1095.51,"py":2187.44,"event":"Position"},{"ts_norm_ms":126,"px":1219.63,"py":2236.06,"event":"Loot"},{"ts_norm_ms":126,"px":1219.63,"py":2236.06,"event":"Position"},{"ts_norm_ms":127,"px":1219.63,"py":2236.06,"event":"Loot"},{"ts_norm_ms":131,"px":1229.71,"py":2217.41,"event":"Position"},{"ts_norm_ms":131,"px":1230.27,"py":2218.08,"event":"Loot"},{"ts_norm_ms":136,"px":1233.55,"py":2226.48,"event":"Position"},{"ts_norm_ms":136,"px":1233.55,"py":2226.48,"event":"Loot"},{"ts_norm_ms":137,"px":1233.55,"py":2226.48,"event":"Loot"},{"ts_norm_ms":141,"px":1289.06,"py":2242.24,"event":"Position"},{"ts_norm_ms":142,"px":1297.93,"py":2236.72,"event":"Loot"},{"ts_norm_ms":146,"px":1293.81,"py":2251.85,"event":"Position"},{"ts_norm_ms":147,"px":1293.81,"py":2251.85,"event":"Loot"},{"ts_norm_ms":149,"px":1291.58,"py":2273.05,"event":"Loot"},{"ts_norm_ms":151,"px":1292.08,"py":2270.87,"event":"Position"},{"ts_norm_ms":156,"px":1267.19,"py":2275.9,"event":"Position"},{"ts_norm_ms":161,"px":1293.05,"py":2264.88,"event":"Position"},{"ts_norm_ms":166,"px":1308.77,"py":2273.13,"event":"BotKill"},{"ts_norm_ms":166,"px":1308.77,"py":2273.13,"event":"Position"},{"ts_norm_ms":171,"px":1322.32,"py":2275.87,"event":"Position"},{"ts_norm_ms":176,"px":1327.67,"py":2236.88,"event":"Position"},{"ts_norm_ms":180,"px":1331.21,"py":2235.43,"event":"BotKill"},{"ts_norm_ms":181,"px":1328.59,"py":2242.32,"event":"Position"},{"ts_norm_ms":184,"px":1323.89,"py":2244.46,"event":"BotKill"},{"ts_norm_ms":186,"px":1319.08,"py":2251.69,"event":"Position"},{"ts_norm_ms":194,"px":1319.93,"py":2227.06,"event":"Loot"},{"ts_norm_ms":196,"px":1300.06,"py":2198.55,"event":"Position"},{"ts_norm_ms":198,"px":1273.28,"py":2169.32,"event":"Loot"},{"ts_norm_ms":199,"px":1273.28,"py":2169.32,"event":"Loot"},{"ts_norm_ms":201,"px":1314.61,"py":2145.41,"event":"Position"},{"ts_norm_ms":202,"px":1319.99,"py":2148.44,"event":"Loot"},{"ts_norm_ms":203,"px":1319.99,"py":2148.44,"event":"Loot"},{"ts_norm_ms":206,"px":1284.2,"py":2175.87,"event":"Position"},{"ts_norm_ms":210,"px":1310.28,"py":2194.39,"event":"BotKill"},{"ts_norm_ms":211,"px":1304.19,"py":2189.1,"event":"Position"},{"ts_norm_ms":216,"px":1273.8,"py":2181.39,"event":"Position"},{"ts_norm_ms":223,"px":1260.4,"py":2172.99,"event":"BotKill"},{"ts_norm_ms":231,"px":1353.72,"py":2110.74,"event":"Position"},{"ts_norm_ms":232,"px":1353.81,"py":2103.8,"event":"Loot"},{"ts_norm_ms":233,"px":1353.81,"py":2103.8,"event":"Loot"},{"ts_norm_ms":236,"px":1369.38,"py":2077.72,"event":"Position"},{"ts_norm_ms":240,"px":1372.2,"py":2070.85,"event":"BotKill"},{"ts_norm_ms":241,"px":1368.85,"py":2072.16,"event":"Position"},{"ts_norm_ms":246,"px":1354.32,"py":1981.0,"event":"Loot"},{"ts_norm_ms":246,"px":1354.32,"py":1981.0,"event":"Position"},{"ts_norm_ms":247,"px":1354.32,"py":1981.0,"event":"Loot"},{"ts_norm_ms":251,"px":1344.32,"py":2048.97,"event":"Position"},{"ts_norm_ms":257,"px":1395.05,"py":2144.78,"event":"Position"},{"ts_norm_ms":262,"px":1427.04,"py":2279.41,"event":"Position"},{"ts_norm_ms":267,"px":1431.18,"py":2333.55,"event":"Position"},{"ts_norm_ms":281,"px":1449.06,"py":2399.2,"event":"Loot"},{"ts_norm_ms":282,"px":1442.18,"py":2397.09,"event":"Position"},{"ts_norm_ms":282,"px":1439.67,"py":2396.06,"event":"Loot"},{"ts_norm_ms":285,"px":1406.19,"py":2345.23,"event":"Loot"},{"ts_norm_ms":287,"px":1404.88,"py":2348.95,"event":"Position"},{"ts_norm_ms":297,"px":1405.08,"py":2363.86,"event":"Position"},{"ts_norm_ms":312,"px":1400.73,"py":2354.55,"event":"Position"},{"ts_norm_ms":322,"px":1402.76,"py":2350.98,"event":"Loot"},{"ts_norm_ms":327,"px":1426.4,"py":2361.71,"event":"Position"},{"ts_norm_ms":332,"px":1423.16,"py":2326.17,"event":"Position"},{"ts_norm_ms":341,"px":1428.99,"py":2328.2,"event":"BotKill"},{"ts_norm_ms":347,"px":1447.46,"py":2299.32,"event":"Position"},{"ts_norm_ms":352,"px":1456.64,"py":2286.72,"event":"Loot"},{"ts_norm_ms":352,"px":1456.64,"py":2286.72,"event":"Position"},{"ts_norm_ms":357,"px":1521.11,"py":2259.61,"event":"Position"},{"ts_norm_ms":362,"px":1554.55,"py":2166.0,"event":"Position"},{"ts_norm_ms":367,"px":1529.77,"py":2144.21,"event":"Position"},{"ts_norm_ms":368,"px":1529.33,"py":2136.78,"event":"BotKill"},{"ts_norm_ms":372,"px":1550.51,"py":2123.36,"event":"Position"},{"ts_norm_ms":374,"px":1550.63,"py":2123.05,"event":"BotKill"},{"ts_norm_ms":375,"px":1550.63,"py":2123.05,"event":"BotKill"},{"ts_norm_ms":377,"px":1543.25,"py":2147.14,"event":"Position"},{"ts_norm_ms":382,"px":1496.54,"py":2248.96,"event":"Position"},{"ts_norm_ms":387,"px":1464.55,"py":2274.56,"event":"Position"},{"ts_norm_ms":388,"px":1464.55,"py":2274.56,"event":"Loot"},{"ts_norm_ms":389,"px":1464.55,"py":2274.56,"event":"Loot"},{"ts_norm_ms":390,"px":1464.55,"py":2274.56,"event":"Loot"},{"ts_norm_ms":395,"px":1525.47,"py":2288.22,"event":"Loot"},{"ts_norm_ms":397,"px":1553.88,"py":2269.14,"event":"Position"},{"ts_norm_ms":398,"px":1556.14,"py":2269.2,"event":"Loot"},{"ts_norm_ms":402,"px":1560.49,"py":2339.82,"event":"Position"},{"ts_norm_ms":407,"px":1551.57,"py":2304.68,"event":"Position"},{"ts_norm_ms":414,"px":1565.51,"py":2301.46,"event":"BotKill"},{"ts_norm_ms":417,"px":1560.02,"py":2325.26,"event":"Position"},{"ts_norm_ms":419,"px":1550.96,"py":2355.09,"event":"Loot"},{"ts_norm_ms":420,"px":1550.96,"py":2355.09,"event":"Loot"},{"ts_norm_ms":422,"px":1529.96,"py":2353.06,"event":"Loot"},{"ts_norm_ms":422,"px":1529.96,"py":2353.06,"event":"Position"},{"ts_norm_ms":428,"px":1534.64,"py":2291.83,"event":"Position"},{"ts_norm_ms":428,"px":1534.64,"py":2291.83,"event":"Loot"},{"ts_norm_ms":433,"px":1559.52,"py":2299.31,"event":"Position"},{"ts_norm_ms":438,"px":1602.22,"py":2357.56,"event":"Position"},{"ts_norm_ms":443,"px":1601.59,"py":2385.32,"event":"Position"},{"ts_norm_ms":451,"px":1601.59,"py":2385.32,"event":"Loot"},{"ts_norm_ms":458,"px":1606.16,"py":2389.45,"event":"Position"},{"ts_norm_ms":463,"px":1614.71,"py":2349.66,"event":"Position"},{"ts_norm_ms":468,"px":1588.86,"py":2368.38,"event":"Position"},{"ts_norm_ms":473,"px":1583.46,"py":2380.58,"event":"Position"},{"ts_norm_ms":474,"px":1579.82,"py":2378.66,"event":"BotKill"},{"ts_norm_ms":478,"px":1586.0,"py":2369.6,"event":"Position"},{"ts_norm_ms":482,"px":1654.03,"py":2323.3,"event":"Loot"},{"ts_norm_ms":483,"px":1653.24,"py":2322.32,"event":"Position"},{"ts_norm_ms":488,"px":1653.54,"py":2281.98,"event":"Position"},{"ts_norm_ms":493,"px":1659.66,"py":2202.51,"event":"Position"},{"ts_norm_ms":498,"px":1684.04,"py":2180.18,"event":"BotKill"},{"ts_norm_ms":498,"px":1684.04,"py":2180.18,"event":"Position"},{"ts_norm_ms":503,"px":1664.29,"py":2177.04,"event":"Position"},{"ts_norm_ms":513,"px":1660.57,"py":2165.42,"event":"Position"},{"ts_norm_ms":518,"px":1676.11,"py":2283.29,"event":"Position"},{"ts_norm_ms":519,"px":1686.41,"py":2288.77,"event":"Loot"},{"ts_norm_ms":523,"px":1644.4,"py":2266.98,"event":"Position"},{"ts_norm_ms":528,"px":1564.09,"py":2342.21,"event":"Position"},{"ts_norm_ms":533,"px":1549.9,"py":2348.28,"event":"Position"},{"ts_norm_ms":538,"px":1636.99,"py":2315.07,"event":"Position"},{"ts_norm_ms":543,"px":1694.07,"py":2292.27,"event":"Position"},{"ts_norm_ms":548,"px":1744.72,"py":2207.84,"event":"Position"},{"ts_norm_ms":553,"px":1762.74,"py":2157.43,"event":"Position"},{"ts_norm_ms":558,"px":1761.47,"py":2127.2,"event":"Position"},{"ts_norm_ms":563,"px":1751.07,"py":2131.05,"event":"Position"},{"ts_norm_ms":565,"px":1765.69,"py":2104.08,"event":"BotKill"},{"ts_norm_ms":568,"px":1773.89,"py":2087.75,"event":"Position"},{"ts_norm_ms":568,"px":1773.89,"py":2087.75,"event":"Loot"},{"ts_norm_ms":569,"px":1775.15,"py":2084.67,"event":"BotKill"},{"ts_norm_ms":573,"px":1786.99,"py":2060.53,"event":"Position"},{"ts_norm_ms":578,"px":1749.58,"py":2051.67,"event":"Position"},{"ts_norm_ms":579,"px":1749.58,"py":2051.67,"event":"Loot"},{"ts_norm_ms":581,"px":1754.52,"py":2058.63,"event":"BotKill"},{"ts_norm_ms":583,"px":1747.11,"py":2044.96,"event":"Position"},{"ts_norm_ms":588,"px":1800.36,"py":2078.16,"event":"Position"},{"ts_norm_ms":598,"px":1754.17,"py":2058.61,"event":"Position"},{"ts_norm_ms":603,"px":1632.64,"py":2095.46,"event":"Position"},{"ts_norm_ms":609,"px":1584.0,"py":2175.29,"event":"Position"},{"ts_norm_ms":614,"px":1404.62,"py":2100.03,"event":"Position"},{"ts_norm_ms":619,"px":1264.57,"py":2088.31,"event":"Position"},{"ts_norm_ms":624,"px":1163.49,"py":2101.47,"event":"Position"},{"ts_norm_ms":629,"px":1109.99,"py":2168.74,"event":"Position"},{"ts_norm_ms":630,"px":1109.99,"py":2168.74,"event":"Loot"},{"ts_norm_ms":633,"px":1100.44,"py":2167.05,"event":"Loot"},{"ts_norm_ms":634,"px":1100.44,"py":2167.05,"event":"Position"},{"ts_norm_ms":639,"px":1000.95,"py":2086.94,"event":"Position"},{"ts_norm_ms":644,"px":870.18,"py":2035.53,"event":"Position"},{"ts_norm_ms":649,"px":807.62,"py":1925.23,"event":"Position"},{"ts_norm_ms":654,"px":714.12,"py":1884.7,"event":"Position"},{"ts_norm_ms":659,"px":642.94,"py":1876.09,"event":"Position"},{"ts_norm_ms":664,"px":561.94,"py":1773.86,"event":"Position"},{"ts_norm_ms":669,"px":593.66,"py":1751.81,"event":"Position"},{"ts_norm_ms":674,"px":630.63,"py":1805.17,"event":"Position"}]}],"human_count":1,"bot_count":0,"total_events":179}