{"match_id":"2d0e75c5-d51e-4434-aad4-b3e683c300bc","map_id":"GrandRift","date":"February_10","players":[{"user_id":"94d042cb-a0f2-45f3-bdca-42fab73cfef5","match_id":"2d0e75c5-d51e-4434-aad4-b3e683c300bc","map_id":"GrandRift","date":"February_10","is_bot":false,"events":[{"ts_norm_ms":0,"px":673.66,"py":817.54,"event":"Position"},{"ts_norm_ms":35,"px":639.48,"py":790.97,"event":"Position"},{"ts_norm_ms":40,"px":575.87,"py":774.91,"event":"Position"},{"ts_norm_ms":45,"px":583.31,"py":826.52,"event":"Position"},{"ts_norm_ms":45,"px":583.31,"py":826.52,"event":"Loot"},{"ts_norm_ms":46,"px":583.31,"py":826.52,"event":"Loot"},{"ts_norm_ms":50,"px":566.08,"py":838.31,"event":"Position"},{"ts_norm_ms":51,"px":566.08,"py":838.31,"event":"Loot"},{"ts_norm_ms":55,"px":545.49,"py":817.35,"event":"Position"},{"ts_norm_ms":59,"px":557.78,"py":844.39,"event":"Loot"},{"ts_norm_ms":60,"px":565.27,"py":859.12,"event":"Position"},{"ts_norm_ms":65,"px":529.65,"py":929.06,"event":"Position"},{"ts_norm_ms":70,"px":485.39,"py":944.88,"event":"Position"},{"ts_norm_ms":75,"px":453.97,"py":973.84,"event":"Position"},{"ts_norm_ms":76,"px":453.97,"py":973.84,"event":"Loot"},{"ts_norm_ms":80,"px":454.83,"py":990.89,"event":"Position"},{"ts_norm_ms":85,"px":523.5,"py":1019.95,"event":"Position"},{"ts_norm_ms":90,"px":517.81,"py":1083.92,"event":"Position"},{"ts_norm_ms":95,"px":458.03,"py":1082.11,"event":"Position"},{"ts_norm_ms":100,"px":381.64,"py":1028.81,"event":"Position"},{"ts_norm_ms":105,"px":414.19,"py":913.91,"event":"Position"},{"ts_norm_ms":110,"px":460.03,"py":849.62,"event":"Position"},{"ts_norm_ms":115,"px":553.72,"py":791.39,"event":"Position"},{"ts_norm_ms":120,"px":570.79,"py":745.75,"event":"Position"},{"ts_norm_ms":130,"px":576.28,"py":746.74,"event":"Position"},{"ts_norm_ms":135,"px":608.29,"py":759.48,"event":"Position"},{"ts_norm_ms":140,"px":558.05,"py":805.75,"event":"Position"},{"ts_norm_ms":145,"px":555.17,"py":838.73,"event":"Position"},{"ts_norm_ms":150,"px":548.18,"py":840.95,"event":"Position"},{"ts_norm_ms":176,"px":549.25,"py":838.53,"event":"Position"},{"ts_norm_ms":180,"px":548.68,"py":835.04,"event":"BotKill"},{"ts_norm_ms":183,"px":549.31,"py":827.83,"event":"Loot"},{"ts_norm_ms":184,"px":549.31,"py":827.83,"event":"Loot"},{"ts_norm_ms":191,"px":551.41,"py":839.5,"event":"Position"},{"ts_norm_ms":201,"px":548.5,"py":838.07,"event":"BotKill"},{"ts_norm_ms":201,"px":548.5,"py":838.07,"event":"Position"},{"ts_norm_ms":205,"px":548.13,"py":826.6,"event":"Loot"},{"ts_norm_ms":211,"px":568.72,"py":827.62,"event":"Position"},{"ts_norm_ms":216,"px":592.58,"py":913.83,"event":"Position"},{"ts_norm_ms":221,"px":646.13,"py":1026.63,"event":"Position"},{"ts_norm_ms":226,"px":747.35,"py":1062.02,"event":"Position"},{"ts_norm_ms":230,"px":780.55,"py":1047.63,"event":"Loot"},{"ts_norm_ms":231,"px":780.55,"py":1047.63,"event":"Position"},{"ts_norm_ms":231,"px":780.55,"py":1047.63,"event":"Loot"},{"ts_norm_ms":236,"px":799.09,"py":1015.15,"event":"Position"},{"ts_norm_ms":238,"px":799.09,"py":1015.15,"event":"Loot"},{"ts_norm_ms":241,"px":849.88,"py":1020.49,"event":"Position"},{"ts_norm_ms":246,"px":966.7,"py":1037.63,"event":"Position"},{"ts_norm_ms":251,"px":968.24,"py":994.96,"event":"Position"},{"ts_norm_ms":256,"px":979.08,"py":947.89,"event":"Position"},{"ts_norm_ms":261,"px":1007.23,"py":933.87,"event":"Position"},{"ts_norm_ms":271,"px":1006.26,"py":909.95,"event":"Position"},{"ts_norm_ms":281,"px":1019.96,"py":929.53,"event":"Position"},{"ts_norm_ms":286,"px":1023.58,"py":927.45,"event":"Position"},{"ts_norm_ms":291,"px":1121.01,"py":1043.69,"event":"Position"},{"ts_norm_ms":293,"px":1134.24,"py":1058.88,"event":"Loot"},{"ts_norm_ms":301,"px":1025.27,"py":933.58,"event":"Position"},{"ts_norm_ms":306,"px":1107.48,"py":1029.91,"event":"Position"},{"ts_norm_ms":316,"px":1023.99,"py":932.09,"event":"Position"},{"ts_norm_ms":321,"px":1007.83,"py":911.16,"event":"Position"},{"ts_norm_ms":326,"px":1086.5,"py":1005.15,"event":"Position"},{"ts_norm_ms":331,"px":1120.17,"py":1033.48,"event":"Position"},{"ts_norm_ms":334,"px":1122.52,"py":1033.39,"event":"BotKill"},{"ts_norm_ms":339,"px":1119.39,"py":993.93,"event":"Loot"},{"ts_norm_ms":346,"px":1121.39,"py":1033.59,"event":"BotKill"},{"ts_norm_ms":364,"px":1123.93,"py":1036.25,"event":"BotKill"},{"ts_norm_ms":382,"px":1143.97,"py":1001.38,"event":"Position"},{"ts_norm_ms":384,"px":1139.81,"py":957.49,"event":"BotKilled"},{"ts_norm_ms":387,"px":1139.31,"py":956.32,"event":"Position"}]}],"human_count":1,"bot_count":0,"total_events":69}