{"match_id":"6ef9ce85-6dfa-46b3-a176-18965be5d5e7","map_id":"AmbroseValley","date":"February_11","players":[{"user_id":"94d042cb-a0f2-45f3-bdca-42fab73cfef5","match_id":"6ef9ce85-6dfa-46b3-a176-18965be5d5e7","map_id":"AmbroseValley","date":"February_11","is_bot":false,"events":[{"ts_norm_ms":0,"px":329.41,"py":3731.29,"event":"Position"},{"ts_norm_ms":20,"px":393.24,"py":3710.07,"event":"Position"},{"ts_norm_ms":25,"px":542.04,"py":3669.68,"event":"Position"},{"ts_norm_ms":30,"px":589.31,"py":3651.54,"event":"Position"},{"ts_norm_ms":35,"px":660.59,"py":3634.92,"event":"Position"},{"ts_norm_ms":37,"px":687.2,"py":3627.28,"event":"Loot"},{"ts_norm_ms":40,"px":623.5,"py":3662.5,"event":"Position"},{"ts_norm_ms":43,"px":621.25,"py":3657.34,"event":"Loot"},{"ts_norm_ms":45,"px":657.28,"py":3693.64,"event":"Position"},{"ts_norm_ms":50,"px":729.56,"py":3695.72,"event":"Loot"},{"ts_norm_ms":50,"px":727.0,"py":3695.58,"event":"Position"},{"ts_norm_ms":55,"px":709.7,"py":3675.61,"event":"Position"},{"ts_norm_ms":60,"px":744.28,"py":3649.7,"event":"Position"},{"ts_norm_ms":65,"px":738.95,"py":3639.05,"event":"Position"},{"ts_norm_ms":70,"px":762.04,"py":3641.38,"event":"BotKill"},{"ts_norm_ms":70,"px":762.04,"py":3641.38,"event":"Position"},{"ts_norm_ms":76,"px":679.65,"py":3674.37,"event":"Position"},{"ts_norm_ms":77,"px":679.65,"py":3674.37,"event":"Loot"},{"ts_norm_ms":81,"px":707.84,"py":3600.15,"event":"Position"},{"ts_norm_ms":83,"px":705.03,"py":3593.32,"event":"Loot"},{"ts_norm_ms":86,"px":687.31,"py":3620.05,"event":"Position"},{"ts_norm_ms":90,"px":757.96,"py":3546.9,"event":"Loot"},{"ts_norm_ms":91,"px":763.84,"py":3551.37,"event":"Position"},{"ts_norm_ms":92,"px":791.68,"py":3577.71,"event":"Loot"},{"ts_norm_ms":95,"px":858.4,"py":3579.86,"event":"Loot"},{"ts_norm_ms":96,"px":858.4,"py":3579.86,"event":"Position"},{"ts_norm_ms":101,"px":888.81,"py":3613.0,"event":"Position"},{"ts_norm_ms":106,"px":946.12,"py":3659.77,"event":"Position"},{"ts_norm_ms":109,"px":953.83,"py":3683.62,"event":"Loot"},{"ts_norm_ms":111,"px":955.14,"py":3643.67,"event":"Position"},{"ts_norm_ms":116,"px":1006.08,"py":3661.22,"event":"Position"},{"ts_norm_ms":121,"px":1161.43,"py":3675.79,"event":"Position"},{"ts_norm_ms":126,"px":1297.65,"py":3723.54,"event":"Position"},{"ts_norm_ms":131,"px":1423.45,"py":3756.02,"event":"Position"},{"ts_norm_ms":136,"px":1502.68,"py":3763.21,"event":"Position"},{"ts_norm_ms":140,"px":1514.56,"py":3751.71,"event":"Loot"},{"ts_norm_ms":141,"px":1504.1,"py":3736.62,"event":"Position"},{"ts_norm_ms":142,"px":1494.64,"py":3727.44,"event":"Loot"},{"ts_norm_ms":146,"px":1538.76,"py":3720.49,"event":"Position"},{"ts_norm_ms":148,"px":1538.17,"py":3717.48,"event":"Loot"},{"ts_norm_ms":151,"px":1556.28,"py":3738.11,"event":"Position"},{"ts_norm_ms":151,"px":1553.49,"py":3737.72,"event":"Loot"},{"ts_norm_ms":154,"px":1570.73,"py":3775.7,"event":"Loot"},{"ts_norm_ms":155,"px":1579.83,"py":3774.52,"event":"Loot"},{"ts_norm_ms":156,"px":1575.2,"py":3761.6,"event":"Position"},{"ts_norm_ms":159,"px":1569.93,"py":3750.62,"event":"Loot"},{"ts_norm_ms":161,"px":1591.91,"py":3755.12,"event":"Position"},{"ts_norm_ms":166,"px":1577.21,"py":3806.24,"event":"Position"},{"ts_norm_ms":171,"px":1529.71,"py":3806.57,"event":"Position"},{"ts_norm_ms":176,"px":1622.79,"py":3728.56,"event":"Position"},{"ts_norm_ms":181,"px":1649.69,"py":3580.42,"event":"Position"},{"ts_norm_ms":186,"px":1711.47,"py":3478.49,"event":"Position"},{"ts_norm_ms":189,"px":1706.24,"py":3440.86,"event":"Loot"},{"ts_norm_ms":191,"px":1721.71,"py":3439.41,"event":"Position"},{"ts_norm_ms":196,"px":1745.88,"py":3423.18,"event":"Loot"},{"ts_norm_ms":196,"px":1745.88,"py":3423.18,"event":"Position"},{"ts_norm_ms":200,"px":1773.67,"py":3377.33,"event":"Loot"},{"ts_norm_ms":201,"px":1749.44,"py":3398.38,"event":"Position"},{"ts_norm_ms":203,"px":1722.0,"py":3364.36,"event":"Loot"},{"ts_norm_ms":206,"px":1756.53,"py":3408.81,"event":"Position"},{"ts_norm_ms":211,"px":1691.53,"py":3400.63,"event":"Position"},{"ts_norm_ms":212,"px":1691.53,"py":3400.63,"event":"Loot"},{"ts_norm_ms":213,"px":1714.09,"py":3397.67,"event":"Loot"},{"ts_norm_ms":216,"px":1726.65,"py":3405.82,"event":"Position"},{"ts_norm_ms":219,"px":1743.25,"py":3373.84,"event":"Loot"},{"ts_norm_ms":221,"px":1730.21,"py":3381.49,"event":"Position"},{"ts_norm_ms":226,"px":1770.43,"py":3346.07,"event":"Position"},{"ts_norm_ms":231,"px":1784.51,"py":3420.82,"event":"Position"},{"ts_norm_ms":236,"px":1794.32,"py":3554.76,"event":"Position"},{"ts_norm_ms":241,"px":1884.57,"py":3592.77,"event":"Position"},{"ts_norm_ms":246,"px":1984.5,"py":3642.45,"event":"Position"},{"ts_norm_ms":251,"px":2009.55,"py":3592.42,"event":"Position"},{"ts_norm_ms":257,"px":2007.6,"py":3633.66,"event":"Position"},{"ts_norm_ms":257,"px":2007.6,"py":3633.66,"event":"Loot"},{"ts_norm_ms":262,"px":2032.75,"py":3596.3,"event":"Position"},{"ts_norm_ms":267,"px":2056.25,"py":3630.37,"event":"Position"},{"ts_norm_ms":270,"px":2050.04,"py":3648.1,"event":"Loot"},{"ts_norm_ms":272,"px":2039.14,"py":3621.03,"event":"Position"},{"ts_norm_ms":276,"px":2007.88,"py":3629.05,"event":"Loot"},{"ts_norm_ms":277,"px":2006.75,"py":3638.33,"event":"Position"},{"ts_norm_ms":282,"px":1985.38,"py":3664.52,"event":"Position"},{"ts_norm_ms":287,"px":1950.03,"py":3700.91,"event":"Position"},{"ts_norm_ms":292,"px":2060.81,"py":3733.46,"event":"Position"},{"ts_norm_ms":297,"px":2214.78,"py":3742.89,"event":"Position"},{"ts_norm_ms":302,"px":2368.65,"py":3723.36,"event":"Position"},{"ts_norm_ms":307,"px":2426.32,"py":3688.96,"event":"Position"},{"ts_norm_ms":310,"px":2429.47,"py":3659.68,"event":"Loot"},{"ts_norm_ms":312,"px":2460.41,"py":3667.83,"event":"Position"},{"ts_norm_ms":313,"px":2459.7,"py":3667.21,"event":"Loot"},{"ts_norm_ms":317,"px":2488.76,"py":3736.17,"event":"Position"},{"ts_norm_ms":319,"px":2489.58,"py":3737.18,"event":"Loot"},{"ts_norm_ms":322,"px":2442.8,"py":3709.74,"event":"Position"},{"ts_norm_ms":327,"px":2438.48,"py":3760.81,"event":"Position"},{"ts_norm_ms":332,"px":2480.11,"py":3772.65,"event":"Position"},{"ts_norm_ms":337,"px":2578.13,"py":3664.92,"event":"Position"},{"ts_norm_ms":342,"px":2618.74,"py":3535.27,"event":"Position"},{"ts_norm_ms":345,"px":2619.89,"py":3489.42,"event":"Loot"},{"ts_norm_ms":347,"px":2605.21,"py":3457.23,"event":"Position"},{"ts_norm_ms":349,"px":2584.39,"py":3473.52,"event":"Loot"},{"ts_norm_ms":352,"px":2579.36,"py":3453.99,"event":"Position"},{"ts_norm_ms":357,"px":2611.2,"py":3436.49,"event":"Position"},{"ts_norm_ms":362,"px":2602.1,"py":3409.54,"event":"Position"},{"ts_norm_ms":367,"px":2653.73,"py":3349.07,"event":"Position"},{"ts_norm_ms":372,"px":2690.58,"py":3272.48,"event":"Position"},{"ts_norm_ms":377,"px":2702.97,"py":3240.56,"event":"Position"},{"ts_norm_ms":380,"px":2705.78,"py":3241.57,"event":"Loot"},{"ts_norm_ms":381,"px":2704.93,"py":3241.29,"event":"Loot"},{"ts_norm_ms":387,"px":2717.68,"py":3261.73,"event":"Position"},{"ts_norm_ms":391,"px":2736.26,"py":3272.41,"event":"Loot"},{"ts_norm_ms":397,"px":2754.75,"py":3270.94,"event":"Position"},{"ts_norm_ms":402,"px":2703.91,"py":3167.76,"event":"Position"},{"ts_norm_ms":407,"px":2663.14,"py":3025.93,"event":"Position"},{"ts_norm_ms":412,"px":2630.66,"py":2878.22,"event":"Position"},{"ts_norm_ms":417,"px":2529.26,"py":2797.32,"event":"Position"},{"ts_norm_ms":422,"px":2449.56,"py":2718.77,"event":"Position"},{"ts_norm_ms":427,"px":2519.46,"py":2607.88,"event":"Position"},{"ts_norm_ms":433,"px":2512.73,"py":2487.2,"event":"Position"},{"ts_norm_ms":434,"px":2505.9,"py":2479.96,"event":"Loot"},{"ts_norm_ms":436,"px":2487.14,"py":2478.22,"event":"Loot"},{"ts_norm_ms":438,"px":2483.11,"py":2493.83,"event":"Position"},{"ts_norm_ms":443,"px":2460.46,"py":2433.12,"event":"Position"},{"ts_norm_ms":447,"px":2500.75,"py":2396.95,"event":"Loot"},{"ts_norm_ms":448,"px":2508.79,"py":2394.15,"event":"Position"},{"ts_norm_ms":449,"px":2508.5,"py":2402.63,"event":"Loot"},{"ts_norm_ms":451,"px":2502.8,"py":2423.91,"event":"Loot"},{"ts_norm_ms":453,"px":2492.2,"py":2421.61,"event":"Position"},{"ts_norm_ms":453,"px":2495.89,"py":2414.73,"event":"Loot"},{"ts_norm_ms":458,"px":2520.08,"py":2414.93,"event":"Position"},{"ts_norm_ms":463,"px":2549.42,"py":2401.03,"event":"Position"},{"ts_norm_ms":468,"px":2499.89,"py":2368.54,"event":"Loot"},{"ts_norm_ms":468,"px":2499.89,"py":2368.54,"event":"Position"},{"ts_norm_ms":473,"px":2527.23,"py":2350.31,"event":"Position"},{"ts_norm_ms":476,"px":2514.42,"py":2348.38,"event":"Loot"},{"ts_norm_ms":478,"px":2512.57,"py":2351.14,"event":"Position"},{"ts_norm_ms":483,"px":2559.85,"py":2365.61,"event":"Loot"},{"ts_norm_ms":483,"px":2559.85,"py":2365.61,"event":"Position"},{"ts_norm_ms":488,"px":2560.3,"py":2351.68,"event":"Loot"},{"ts_norm_ms":488,"px":2560.3,"py":2351.68,"event":"Position"},{"ts_norm_ms":490,"px":2551.67,"py":2348.6,"event":"Loot"},{"ts_norm_ms":498,"px":2513.71,"py":2355.49,"event":"Position"},{"ts_norm_ms":503,"px":2479.53,"py":2344.04,"event":"Position"},{"ts_norm_ms":508,"px":2468.8,"py":2343.95,"event":"Position"},{"ts_norm_ms":513,"px":2411.11,"py":2353.94,"event":"Position"},{"ts_norm_ms":518,"px":2451.3,"py":2337.53,"event":"Position"},{"ts_norm_ms":523,"px":2480.23,"py":2317.48,"event":"Position"},{"ts_norm_ms":533,"px":2485.44,"py":2342.54,"event":"Position"},{"ts_norm_ms":543,"px":2500.0,"py":2351.56,"event":"Position"},{"ts_norm_ms":548,"px":2494.64,"py":2349.07,"event":"Position"},{"ts_norm_ms":553,"px":2516.77,"py":2354.08,"event":"Position"},{"ts_norm_ms":558,"px":2613.58,"py":2331.4,"event":"Position"},{"ts_norm_ms":563,"px":2620.63,"py":2205.19,"event":"Position"},{"ts_norm_ms":568,"px":2563.76,"py":2069.27,"event":"Position"},{"ts_norm_ms":583,"px":2543.39,"py":2054.56,"event":"Position"},{"ts_norm_ms":587,"px":2543.39,"py":2054.56,"event":"Loot"},{"ts_norm_ms":593,"px":2549.16,"py":2058.37,"event":"Position"},{"ts_norm_ms":597,"px":2549.16,"py":2058.37,"event":"Loot"},{"ts_norm_ms":603,"px":2495.12,"py":1954.0,"event":"Position"},{"ts_norm_ms":609,"px":2370.88,"py":1945.2,"event":"Position"},{"ts_norm_ms":614,"px":2267.52,"py":2021.2,"event":"Position"},{"ts_norm_ms":619,"px":2155.62,"py":2127.13,"event":"Position"},{"ts_norm_ms":624,"px":2091.67,"py":2185.93,"event":"Position"},{"ts_norm_ms":629,"px":2003.02,"py":2175.29,"event":"Position"},{"ts_norm_ms":634,"px":1956.19,"py":2271.17,"event":"Position"},{"ts_norm_ms":639,"px":1946.66,"py":2354.52,"event":"Position"},{"ts_norm_ms":644,"px":1982.85,"py":2386.32,"event":"Position"},{"ts_norm_ms":649,"px":1925.4,"py":2295.47,"event":"Position"},{"ts_norm_ms":654,"px":2011.19,"py":2261.36,"event":"Position"},{"ts_norm_ms":659,"px":2064.06,"py":2234.51,"event":"Position"},{"ts_norm_ms":664,"px":2115.3,"py":2233.37,"event":"Position"},{"ts_norm_ms":669,"px":2128.3,"py":2331.4,"event":"Position"},{"ts_norm_ms":674,"px":2111.72,"py":2458.79,"event":"Position"},{"ts_norm_ms":679,"px":2192.03,"py":2557.72,"event":"Position"},{"ts_norm_ms":684,"px":2331.18,"py":2559.56,"event":"Position"},{"ts_norm_ms":689,"px":2469.52,"py":2568.0,"event":"Position"},{"ts_norm_ms":694,"px":2551.63,"py":2464.84,"event":"Position"},{"ts_norm_ms":699,"px":2576.55,"py":2351.47,"event":"Position"},{"ts_norm_ms":704,"px":2525.04,"py":2362.87,"event":"Position"},{"ts_norm_ms":704,"px":2524.53,"py":2363.51,"event":"Loot"},{"ts_norm_ms":709,"px":2612.32,"py":2325.3,"event":"Position"},{"ts_norm_ms":714,"px":2707.1,"py":2368.82,"event":"Position"},{"ts_norm_ms":719,"px":2671.13,"py":2444.71,"event":"Loot"},{"ts_norm_ms":719,"px":2675.96,"py":2447.23,"event":"Position"},{"ts_norm_ms":724,"px":2729.65,"py":2390.3,"event":"Position"},{"ts_norm_ms":734,"px":2723.44,"py":2383.44,"event":"Position"}]}],"human_count":1,"bot_count":0,"total_events":184}