{"match_id":"ccf962ff-50d2-4dec-8d71-680b5f6aaf9f","map_id":"AmbroseValley","date":"February_13","players":[{"user_id":"16f17a30-c240-440a-8c65-de96557f4d34","match_id":"ccf962ff-50d2-4dec-8d71-680b5f6aaf9f","map_id":"AmbroseValley","date":"February_13","is_bot":false,"events":[{"ts_norm_ms":0,"px":1276.24,"py":3802.23,"event":"Position"},{"ts_norm_ms":16,"px":1348.66,"py":3779.4,"event":"Position"},{"ts_norm_ms":21,"px":1474.87,"py":3754.98,"event":"Position"},{"ts_norm_ms":26,"px":1522.79,"py":3767.48,"event":"Position"},{"ts_norm_ms":27,"px":1522.79,"py":3767.48,"event":"Loot"},{"ts_norm_ms":28,"px":1522.79,"py":3767.48,"event":"Loot"},{"ts_norm_ms":30,"px":1522.79,"py":3773.1,"event":"Loot"},{"ts_norm_ms":34,"px":1515.36,"py":3752.86,"event":"Loot"},{"ts_norm_ms":36,"px":1514.49,"py":3747.82,"event":"Position"},{"ts_norm_ms":39,"px":1493.97,"py":3729.1,"event":"Loot"},{"ts_norm_ms":41,"px":1497.29,"py":3726.06,"event":"Position"},{"ts_norm_ms":41,"px":1497.29,"py":3726.06,"event":"Loot"},{"ts_norm_ms":46,"px":1538.08,"py":3743.87,"event":"Position"},{"ts_norm_ms":49,"px":1569.92,"py":3775.82,"event":"Loot"},{"ts_norm_ms":50,"px":1578.85,"py":3774.9,"event":"Loot"},{"ts_norm_ms":51,"px":1578.85,"py":3774.9,"event":"Position"},{"ts_norm_ms":56,"px":1531.25,"py":3724.35,"event":"Position"},{"ts_norm_ms":61,"px":1519.57,"py":3684.76,"event":"Position"},{"ts_norm_ms":66,"px":1425.79,"py":3684.05,"event":"Position"},{"ts_norm_ms":71,"px":1446.19,"py":3657.6,"event":"Position"},{"ts_norm_ms":76,"px":1529.19,"py":3532.47,"event":"Position"},{"ts_norm_ms":81,"px":1666.85,"py":3511.77,"event":"Position"},{"ts_norm_ms":86,"px":1712.46,"py":3460.48,"event":"Position"},{"ts_norm_ms":89,"px":1702.79,"py":3442.32,"event":"Loot"},{"ts_norm_ms":96,"px":1745.83,"py":3422.91,"event":"Position"},{"ts_norm_ms":98,"px":1745.83,"py":3422.91,"event":"Loot"},{"ts_norm_ms":101,"px":1767.89,"py":3406.98,"event":"Position"},{"ts_norm_ms":104,"px":1755.1,"py":3374.24,"event":"Loot"},{"ts_norm_ms":106,"px":1765.77,"py":3377.99,"event":"Position"},{"ts_norm_ms":107,"px":1773.11,"py":3378.24,"event":"Loot"},{"ts_norm_ms":111,"px":1732.09,"py":3391.81,"event":"Position"},{"ts_norm_ms":114,"px":1720.62,"py":3365.15,"event":"Loot"},{"ts_norm_ms":116,"px":1721.9,"py":3393.56,"event":"Position"},{"ts_norm_ms":121,"px":1734.5,"py":3416.07,"event":"Position"},{"ts_norm_ms":131,"px":1715.6,"py":3406.69,"event":"Position"},{"ts_norm_ms":136,"px":1751.48,"py":3376.34,"event":"Position"},{"ts_norm_ms":140,"px":1756.98,"py":3390.67,"event":"Loot"},{"ts_norm_ms":146,"px":1794.46,"py":3404.99,"event":"Position"},{"ts_norm_ms":151,"px":1788.73,"py":3446.83,"event":"Position"},{"ts_norm_ms":156,"px":1727.71,"py":3458.75,"event":"Position"},{"ts_norm_ms":161,"px":1637.92,"py":3383.5,"event":"Position"},{"ts_norm_ms":166,"px":1583.08,"py":3443.61,"event":"Position"},{"ts_norm_ms":171,"px":1496.13,"py":3438.85,"event":"Position"},{"ts_norm_ms":176,"px":1495.09,"py":3474.98,"event":"Position"},{"ts_norm_ms":182,"px":1488.71,"py":3464.65,"event":"Position"},{"ts_norm_ms":187,"px":1482.59,"py":3475.14,"event":"Position"},{"ts_norm_ms":192,"px":1497.24,"py":3457.36,"event":"Position"},{"ts_norm_ms":197,"px":1574.21,"py":3439.43,"event":"Position"},{"ts_norm_ms":202,"px":1660.67,"py":3440.55,"event":"Position"},{"ts_norm_ms":217,"px":1710.01,"py":3434.3,"event":"Position"},{"ts_norm_ms":226,"px":1717.35,"py":3436.86,"event":"BotKill"},{"ts_norm_ms":228,"px":1716.04,"py":3436.36,"event":"BotKill"},{"ts_norm_ms":230,"px":1719.39,"py":3434.57,"event":"Loot"},{"ts_norm_ms":232,"px":1715.77,"py":3435.7,"event":"Loot"},{"ts_norm_ms":245,"px":1714.34,"py":3438.15,"event":"Loot"},{"ts_norm_ms":248,"px":1715.08,"py":3437.62,"event":"Loot"},{"ts_norm_ms":257,"px":1672.18,"py":3446.86,"event":"Position"},{"ts_norm_ms":262,"px":1562.78,"py":3434.98,"event":"Position"},{"ts_norm_ms":267,"px":1419.94,"py":3434.04,"event":"Position"},{"ts_norm_ms":270,"px":1377.98,"py":3435.0,"event":"Loot"},{"ts_norm_ms":271,"px":1377.98,"py":3435.0,"event":"Loot"},{"ts_norm_ms":272,"px":1377.98,"py":3435.0,"event":"Position"},{"ts_norm_ms":272,"px":1377.98,"py":3435.0,"event":"Loot"},{"ts_norm_ms":277,"px":1447.55,"py":3440.73,"event":"Position"},{"ts_norm_ms":282,"px":1501.48,"py":3487.16,"event":"Position"},{"ts_norm_ms":287,"px":1417.02,"py":3503.73,"event":"Position"},{"ts_norm_ms":292,"px":1323.71,"py":3442.88,"event":"Position"},{"ts_norm_ms":297,"px":1262.2,"py":3377.11,"event":"Position"},{"ts_norm_ms":302,"px":1298.12,"py":3312.66,"event":"Loot"},{"ts_norm_ms":302,"px":1298.12,"py":3312.66,"event":"Position"},{"ts_norm_ms":307,"px":1263.55,"py":3310.95,"event":"Position"},{"ts_norm_ms":327,"px":1253.08,"py":3327.77,"event":"Position"},{"ts_norm_ms":332,"px":1194.59,"py":3372.09,"event":"Position"},{"ts_norm_ms":337,"px":1128.33,"py":3256.41,"event":"Position"},{"ts_norm_ms":342,"px":1096.71,"py":3206.18,"event":"Position"},{"ts_norm_ms":344,"px":1096.71,"py":3206.18,"event":"Loot"},{"ts_norm_ms":358,"px":1021.71,"py":3230.79,"event":"Position"},{"ts_norm_ms":363,"px":982.66,"py":3219.24,"event":"Position"},{"ts_norm_ms":368,"px":993.5,"py":3147.13,"event":"Position"},{"ts_norm_ms":370,"px":991.57,"py":3145.87,"event":"Loot"},{"ts_norm_ms":373,"px":977.96,"py":3150.37,"event":"Position"},{"ts_norm_ms":378,"px":981.52,"py":3199.62,"event":"Position"},{"ts_norm_ms":383,"px":930.49,"py":3260.88,"event":"Position"},{"ts_norm_ms":393,"px":872.04,"py":3217.56,"event":"Position"},{"ts_norm_ms":398,"px":800.77,"py":3188.24,"event":"Position"},{"ts_norm_ms":403,"px":803.71,"py":3205.43,"event":"Position"},{"ts_norm_ms":408,"px":819.46,"py":3201.25,"event":"Position"},{"ts_norm_ms":413,"px":870.26,"py":3102.33,"event":"Position"},{"ts_norm_ms":418,"px":915.23,"py":2999.23,"event":"Position"},{"ts_norm_ms":423,"px":956.51,"py":2901.98,"event":"Position"},{"ts_norm_ms":428,"px":964.84,"py":2773.77,"event":"Position"},{"ts_norm_ms":433,"px":984.59,"py":2657.85,"event":"Position"},{"ts_norm_ms":438,"px":970.79,"py":2517.3,"event":"Position"},{"ts_norm_ms":443,"px":951.63,"py":2448.5,"event":"Position"},{"ts_norm_ms":448,"px":905.03,"py":2378.06,"event":"Position"},{"ts_norm_ms":453,"px":859.62,"py":2274.84,"event":"Position"},{"ts_norm_ms":458,"px":855.47,"py":2228.8,"event":"Position"},{"ts_norm_ms":463,"px":871.55,"py":2194.98,"event":"Position"},{"ts_norm_ms":468,"px":976.31,"py":2159.92,"event":"Position"},{"ts_norm_ms":473,"px":1063.65,"py":2175.9,"event":"Position"},{"ts_norm_ms":478,"px":1152.23,"py":2230.1,"event":"Position"},{"ts_norm_ms":483,"px":1223.48,"py":2254.49,"event":"Position"},{"ts_norm_ms":488,"px":1232.64,"py":2222.47,"event":"Position"},{"ts_norm_ms":488,"px":1233.16,"py":2222.58,"event":"Loot"},{"ts_norm_ms":493,"px":1252.73,"py":2264.38,"event":"Position"},{"ts_norm_ms":494,"px":1246.42,"py":2270.72,"event":"Loot"},{"ts_norm_ms":498,"px":1298.41,"py":2234.32,"event":"Position"},{"ts_norm_ms":499,"px":1298.09,"py":2235.9,"event":"Loot"},{"ts_norm_ms":503,"px":1303.65,"py":2242.15,"event":"Position"},{"ts_norm_ms":508,"px":1334.64,"py":2245.57,"event":"Position"},{"ts_norm_ms":513,"px":1290.42,"py":2137.77,"event":"Position"},{"ts_norm_ms":518,"px":1301.09,"py":2124.35,"event":"Position"},{"ts_norm_ms":523,"px":1289.33,"py":2187.27,"event":"Position"},{"ts_norm_ms":528,"px":1353.68,"py":2147.7,"event":"Position"},{"ts_norm_ms":531,"px":1358.91,"py":2083.62,"event":"Loot"},{"ts_norm_ms":533,"px":1366.78,"py":2070.06,"event":"Position"},{"ts_norm_ms":539,"px":1253.91,"py":2072.73,"event":"Position"},{"ts_norm_ms":549,"px":1263.17,"py":2076.09,"event":"Position"},{"ts_norm_ms":554,"px":1167.41,"py":2067.25,"event":"Position"},{"ts_norm_ms":559,"px":1176.02,"py":2073.82,"event":"Position"},{"ts_norm_ms":564,"px":1260.87,"py":2110.26,"event":"Position"},{"ts_norm_ms":568,"px":1341.25,"py":2096.39,"event":"BotKill"},{"ts_norm_ms":569,"px":1341.25,"py":2096.39,"event":"Position"},{"ts_norm_ms":570,"px":1342.41,"py":2097.91,"event":"Loot"},{"ts_norm_ms":572,"px":1342.41,"py":2097.91,"event":"Loot"},{"ts_norm_ms":574,"px":1351.07,"py":2089.54,"event":"Position"},{"ts_norm_ms":579,"px":1321.17,"py":2119.78,"event":"Position"},{"ts_norm_ms":592,"px":1339.27,"py":2097.63,"event":"Loot"},{"ts_norm_ms":594,"px":1355.25,"py":2085.76,"event":"Position"},{"ts_norm_ms":599,"px":1392.79,"py":2072.1,"event":"Position"},{"ts_norm_ms":604,"px":1481.56,"py":2022.95,"event":"Position"},{"ts_norm_ms":609,"px":1566.17,"py":1910.09,"event":"Position"},{"ts_norm_ms":614,"px":1606.41,"py":1900.64,"event":"Position"},{"ts_norm_ms":619,"px":1595.51,"py":1875.84,"event":"Position"},{"ts_norm_ms":624,"px":1623.12,"py":1845.39,"event":"Position"},{"ts_norm_ms":629,"px":1628.14,"py":1926.51,"event":"Position"},{"ts_norm_ms":634,"px":1716.93,"py":1933.43,"event":"Position"},{"ts_norm_ms":639,"px":1811.72,"py":2030.89,"event":"Position"},{"ts_norm_ms":644,"px":1924.18,"py":2035.43,"event":"Position"},{"ts_norm_ms":649,"px":2033.27,"py":2093.78,"event":"Position"},{"ts_norm_ms":654,"px":2040.74,"py":2199.17,"event":"Position"},{"ts_norm_ms":659,"px":1960.51,"py":2278.7,"event":"Position"},{"ts_norm_ms":664,"px":1973.62,"py":2378.46,"event":"Position"},{"ts_norm_ms":669,"px":2055.33,"py":2421.16,"event":"Position"},{"ts_norm_ms":674,"px":2152.2,"py":2511.73,"event":"Position"},{"ts_norm_ms":679,"px":2295.28,"py":2553.57,"event":"Position"},{"ts_norm_ms":684,"px":2445.37,"py":2563.2,"event":"Position"},{"ts_norm_ms":689,"px":2573.06,"py":2495.12,"event":"Position"},{"ts_norm_ms":694,"px":2609.56,"py":2355.17,"event":"Position"},{"ts_norm_ms":699,"px":2697.59,"py":2344.44,"event":"Position"},{"ts_norm_ms":704,"px":2729.83,"py":2397.68,"event":"Position"},{"ts_norm_ms":710,"px":2729.83,"py":2397.68,"event":"KilledByStorm"}]}],"human_count":1,"bot_count":0,"total_events":152}